Workbook

Sheet Cover
B2: Monte Carlo Simulation of Project NPV
B3: Excel reference model, validated against an independent Python implementation
B5: Project
B6: 5-year investment project: €800,000 invested in Year 0, operations from Year 1 to Year 5.
B7: No taxes, no working capital, no salvage value. Discount rate: 10%.
B8: Annual FCF = Volume × (Price − Variable cost) − Fixed costs. Base-case NPV = €33,973.09.
B9: One draw applies to all five years: the model captures uncertainty about the level of each input, not year-to-year noise.
B11: Key results (live, 5,000 iterations per model)
B12: Model | C12: Mean NPV | D12: P5 | E12: P50 | F12: P95 | G12: P(NPV < 0)
B13: =HYPERLINK("#'Independent'!A1","Independent") -> Independent | C13: =Independent!$C$39 -> 29828.592 | D13: =Independent!$C$41 -> -294870.05 | E13: =Independent!$C$42 -> 25757.624 | F13: =Independent!$C$43 -> 383728.68 | G13: =Independent!$C$46 -> 0.4496
B14: =HYPERLINK("#'Justified'!A1","Justified") -> Justified | C14: =Justified!$C$49 -> -12665.029 | D14: =Justified!$C$51 -> -255052.88 | E14: =Justified!$C$52 -> -12156.814 | F14: =Justified!$C$53 -> 227328.52 | G14: =Justified!$C$56 -> 0.5348
B15: =HYPERLINK("#'Correlated'!A1","Correlated") -> Correlated | C15: =Correlated!$C$54 -> -16730.853 | D15: =Correlated!$C$56 -> -210726.62 | E15: =Correlated!$C$57 -> -19685.516 | F15: =Correlated!$C$58 -> 182281.06 | G15: =Correlated!$C$61 -> 0.5602
B16: With justified distributions, the mean NPV turns negative: the project does not cover its cost of capital in expectation.
B18: Sheet guide
B19: =HYPERLINK("#'Independent'!A1","Independent") -> Independent | C19: Model 1: three independent Normal inputs.
B20: =HYPERLINK("#'Justified'!A1","Justified") -> Justified | C20: Model 2: PERT price, demand capped by capacity, variable cost fitted on historical data.
B21: =HYPERLINK("#'Correlated'!A1","Correlated") -> Correlated | C21: Model 3: Model 2 + Price–Demand correlation through a Gaussian copula (Cholesky).
B22: =HYPERLINK("#'Validation'!A1","Validation") -> Validation | C22: Excel vs Python (1,000,000 iterations) with z-scores.
B24: How each model sheet is organised
B25: 1. Base-case inputs → 2. Distributions (one random draw) → 3. Cash flows and NPV → 4. Results.
B26: Columns L–O: Excel Data Table that re-evaluates the model 5,000 times. Columns Q–V: histogram bins.
B27: Simulation switch (cell C6): 1 = simulation, 0 = deterministic base case.
B28: Calculation mode is 'Automatic except for data tables': press F9 (Mac: Cmd + =) to rerun the simulation.
B30: Colour code
B31: 1,234 | C31: Hard-coded input
B32: 1,234 | C32: Formula
B33: 1,234 | C33: Link to another sheet
B34: 1 | C34: Switch or key lever
B35: 1,234 | C35: Key output
B37: Python implementation, dashboard and ASML case study: github.com/YacineHaddouche/monte-carlo-valuation

Sheet Independent
B1: Model 1 — Three independent normal inputs
B2: Price, volume and variable cost each drawn from a Normal distribution, independently.
B3: Blue = input · Black = formula · Yellow fill = switch / key lever · Press F9 (Mac: Cmd + =) to rerun the 5,000 iterations.
L4: Simulation (Data Table) | Q4: Histogram bins
B5: 1. Base-case inputs | L5: Iteration | M5: NPV | Q5: Bin width (€, auto) | R5: =ROUNDUP((MAX($M$7:$M$5006)-MIN($M$7:$M$5006))/30/10000,0)*10000 -> 60000
B6: Simulation switch (1 = simulation, 0 = base case) | C6: 1 | D6: ← 0 = base case, 1 = simulation | M6: =$C$30 -> 264992.64 | Q6: Lower (€) | R6: Upper (€) | S6: Midpoint | T6: Count | U6: NPV < 0 | V6: NPV ≥ 0
B7: Initial investment (€, Year 0) | C7: 800000 | L7: 1 | M7: -180016.76 | Q7: =INT(MIN($M$7:$M$5006)/$R$5)*$R$5 -> -660000 | R7: =Q7+$R$5 -> -600000 | S7: =TEXT((Q7+R7)/2000,"#,##0")&"k" -> -630k | T7: =COUNTIFS($M$7:$M$5006,">="&Q7,$M$7:$M$5006,"<"&R7) -> 1 | U7: =IF(R7<=0,T7/COUNT($M$7:$M$5006),0) -> 0.0002 | V7: =IF(Q7>=0,T7/COUNT($M$7:$M$5006),0) -> 0
B8: Volume (units / year) | C8: 15000 | L8: 2 | M8: 98600.559 | Q8: =R7 -> -600000 | R8: =Q8+$R$5 -> -540000 | S8: =TEXT((Q8+R8)/2000,"#,##0")&"k" -> -570k | T8: =COUNTIFS($M$7:$M$5006,">="&Q8,$M$7:$M$5006,"<"&R8) -> 5 | U8: =IF(R8<=0,T8/COUNT($M$7:$M$5006),0) -> 0.001 | V8: =IF(Q8>=0,T8/COUNT($M$7:$M$5006),0) -> 0
B9: Price (€ / unit) | C9: 50 | L9: 3 | M9: -14857.307 | Q9: =R8 -> -540000 | R9: =Q9+$R$5 -> -480000 | S9: =TEXT((Q9+R9)/2000,"#,##0")&"k" -> -510k | T9: =COUNTIFS($M$7:$M$5006,">="&Q9,$M$7:$M$5006,"<"&R9) -> 4 | U9: =IF(R9<=0,T9/COUNT($M$7:$M$5006),0) -> 0.0008 | V9: =IF(Q9>=0,T9/COUNT($M$7:$M$5006),0) -> 0
B10: Variable cost (€ / unit) | C10: 30 | L10: 4 | M10: 263833.98 | Q10: =R9 -> -480000 | R10: =Q10+$R$5 -> -420000 | S10: =TEXT((Q10+R10)/2000,"#,##0")&"k" -> -450k | T10: =COUNTIFS($M$7:$M$5006,">="&Q10,$M$7:$M$5006,"<"&R10) -> 31 | U10: =IF(R10<=0,T10/COUNT($M$7:$M$5006),0) -> 0.0062 | V10: =IF(Q10>=0,T10/COUNT($M$7:$M$5006),0) -> 0
B11: Fixed costs (€ / year) | C11: 80000 | L11: 5 | M11: 170730.78 | Q11: =R10 -> -420000 | R11: =Q11+$R$5 -> -360000 | S11: =TEXT((Q11+R11)/2000,"#,##0")&"k" -> -390k | T11: =COUNTIFS($M$7:$M$5006,">="&Q11,$M$7:$M$5006,"<"&R11) -> 62 | U11: =IF(R11<=0,T11/COUNT($M$7:$M$5006),0) -> 0.0124 | V11: =IF(Q11>=0,T11/COUNT($M$7:$M$5006),0) -> 0
B12: Discount rate | C12: 0.1 | L12: 6 | M12: -64816.156 | Q12: =R11 -> -360000 | R12: =Q12+$R$5 -> -300000 | S12: =TEXT((Q12+R12)/2000,"#,##0")&"k" -> -330k | T12: =COUNTIFS($M$7:$M$5006,">="&Q12,$M$7:$M$5006,"<"&R12) -> 135 | U12: =IF(R12<=0,T12/COUNT($M$7:$M$5006),0) -> 0.027 | V12: =IF(Q12>=0,T12/COUNT($M$7:$M$5006),0) -> 0
L13: 7 | M13: -49083.233 | Q13: =R12 -> -300000 | R13: =Q13+$R$5 -> -240000 | S13: =TEXT((Q13+R13)/2000,"#,##0")&"k" -> -270k | T13: =COUNTIFS($M$7:$M$5006,">="&Q13,$M$7:$M$5006,"<"&R13) -> 226 | U13: =IF(R13<=0,T13/COUNT($M$7:$M$5006),0) -> 0.0452 | V13: =IF(Q13>=0,T13/COUNT($M$7:$M$5006),0) -> 0
B14: 2. Uncertain inputs and distributions | L14: 8 | M14: 50663.793 | Q14: =R13 -> -240000 | R14: =Q14+$R$5 -> -180000 | S14: =TEXT((Q14+R14)/2000,"#,##0")&"k" -> -210k | T14: =COUNTIFS($M$7:$M$5006,">="&Q14,$M$7:$M$5006,"<"&R14) -> 335 | U14: =IF(R14<=0,T14/COUNT($M$7:$M$5006),0) -> 0.067 | V14: =IF(Q14>=0,T14/COUNT($M$7:$M$5006),0) -> 0
B15: Input | C15: Distribution | D15: Mean | E15: SD | F15: Min | G15: Mode | H15: Max | I15: Draw | J15: Value used | L15: 9 | M15: -111737.95 | Q15: =R14 -> -180000 | R15: =Q15+$R$5 -> -120000 | S15: =TEXT((Q15+R15)/2000,"#,##0")&"k" -> -150k | T15: =COUNTIFS($M$7:$M$5006,">="&Q15,$M$7:$M$5006,"<"&R15) -> 379 | U15: =IF(R15<=0,T15/COUNT($M$7:$M$5006),0) -> 0.0758 | V15: =IF(Q15>=0,T15/COUNT($M$7:$M$5006),0) -> 0
B16: Price (€ / unit) | C16: Normal | D16: 50 | E16: 2.5 | I16: =_xlfn.NORM.INV(RAND(),D16,E16) -> 54.29756 | J16: =IF($C$6=1,I16,$C$9) -> 54.29756 | L16: 10 | M16: -109215.94 | Q16: =R15 -> -120000 | R16: =Q16+$R$5 -> -60000 | S16: =TEXT((Q16+R16)/2000,"#,##0")&"k" -> -90k | T16: =COUNTIFS($M$7:$M$5006,">="&Q16,$M$7:$M$5006,"<"&R16) -> 480 | U16: =IF(R16<=0,T16/COUNT($M$7:$M$5006),0) -> 0.096 | V16: =IF(Q16>=0,T16/COUNT($M$7:$M$5006),0) -> 0
B17: Volume (units / year) | C17: Normal | D17: 15000 | E17: 1500 | I17: =_xlfn.NORM.INV(RAND(),D17,E17) -> 14004.733 | J17: =IF($C$6=1,I17,$C$8) -> 14004.733 | L17: 11 | M17: 124782.57 | Q17: =R16 -> -60000 | R17: =Q17+$R$5 -> 0 | S17: =TEXT((Q17+R17)/2000,"#,##0")&"k" -> -30k | T17: =COUNTIFS($M$7:$M$5006,">="&Q17,$M$7:$M$5006,"<"&R17) -> 590 | U17: =IF(R17<=0,T17/COUNT($M$7:$M$5006),0) -> 0.118 | V17: =IF(Q17>=0,T17/COUNT($M$7:$M$5006),0) -> 0
B18: Variable cost (€ / unit) | C18: Normal | D18: 30 | E18: 1.5 | I18: =_xlfn.NORM.INV(RAND(),D18,E18) -> 28.524675 | J18: =IF($C$6=1,I18,$C$10) -> 28.524675 | L18: 12 | M18: 421758.09 | Q18: =R17 -> 0 | R18: =Q18+$R$5 -> 60000 | S18: =TEXT((Q18+R18)/2000,"#,##0")&"k" -> 30k | T18: =COUNTIFS($M$7:$M$5006,">="&Q18,$M$7:$M$5006,"<"&R18) -> 636 | U18: =IF(R18<=0,T18/COUNT($M$7:$M$5006),0) -> 0 | V18: =IF(Q18>=0,T18/COUNT($M$7:$M$5006),0) -> 0.1272
L19: 13 | M19: -98507.78 | Q19: =R18 -> 60000 | R19: =Q19+$R$5 -> 120000 | S19: =TEXT((Q19+R19)/2000,"#,##0")&"k" -> 90k | T19: =COUNTIFS($M$7:$M$5006,">="&Q19,$M$7:$M$5006,"<"&R19) -> 532 | U19: =IF(R19<=0,T19/COUNT($M$7:$M$5006),0) -> 0 | V19: =IF(Q19>=0,T19/COUNT($M$7:$M$5006),0) -> 0.1064
B20: 3. Cash flows and NPV (one draw) | L20: 14 | M20: -44226.845 | Q20: =R19 -> 120000 | R20: =Q20+$R$5 -> 180000 | S20: =TEXT((Q20+R20)/2000,"#,##0")&"k" -> 150k | T20: =COUNTIFS($M$7:$M$5006,">="&Q20,$M$7:$M$5006,"<"&R20) -> 490 | U20: =IF(R20<=0,T20/COUNT($M$7:$M$5006),0) -> 0 | V20: =IF(Q20>=0,T20/COUNT($M$7:$M$5006),0) -> 0.098
B21: € | C21: Year 0 | D21: Year 1 | E21: Year 2 | F21: Year 3 | G21: Year 4 | H21: Year 5 | L21: 15 | M21: -45727.614 | Q21: =R20 -> 180000 | R21: =Q21+$R$5 -> 240000 | S21: =TEXT((Q21+R21)/2000,"#,##0")&"k" -> 210k | T21: =COUNTIFS($M$7:$M$5006,">="&Q21,$M$7:$M$5006,"<"&R21) -> 336 | U21: =IF(R21<=0,T21/COUNT($M$7:$M$5006),0) -> 0 | V21: =IF(Q21>=0,T21/COUNT($M$7:$M$5006),0) -> 0.0672
B22: Initial investment | C22: =-$C$7 -> -800000 | D22: 0 | E22: 0 | F22: 0 | G22: 0 | H22: 0 | L22: 16 | M22: 154355.71 | Q22: =R21 -> 240000 | R22: =Q22+$R$5 -> 300000 | S22: =TEXT((Q22+R22)/2000,"#,##0")&"k" -> 270k | T22: =COUNTIFS($M$7:$M$5006,">="&Q22,$M$7:$M$5006,"<"&R22) -> 284 | U22: =IF(R22<=0,T22/COUNT($M$7:$M$5006),0) -> 0 | V22: =IF(Q22>=0,T22/COUNT($M$7:$M$5006),0) -> 0.0568
B23: Revenue (units × price) | C23: 0 | D23: =$J$17*$J$16 -> 760422.83 | E23: =$J$17*$J$16 -> 760422.83 | F23: =$J$17*$J$16 -> 760422.83 | G23: =$J$17*$J$16 -> 760422.83 | H23: =$J$17*$J$16 -> 760422.83 | L23: 17 | M23: 394861.48 | Q23: =R22 -> 300000 | R23: =Q23+$R$5 -> 360000 | S23: =TEXT((Q23+R23)/2000,"#,##0")&"k" -> 330k | T23: =COUNTIFS($M$7:$M$5006,">="&Q23,$M$7:$M$5006,"<"&R23) -> 179 | U23: =IF(R23<=0,T23/COUNT($M$7:$M$5006),0) -> 0 | V23: =IF(Q23>=0,T23/COUNT($M$7:$M$5006),0) -> 0.0358
B24: Variable costs (units × variable cost) | C24: 0 | D24: =-$J$17*$J$18 -> -399480.45 | E24: =-$J$17*$J$18 -> -399480.45 | F24: =-$J$17*$J$18 -> -399480.45 | G24: =-$J$17*$J$18 -> -399480.45 | H24: =-$J$17*$J$18 -> -399480.45 | L24: 18 | M24: 30647.353 | Q24: =R23 -> 360000 | R24: =Q24+$R$5 -> 420000 | S24: =TEXT((Q24+R24)/2000,"#,##0")&"k" -> 390k | T24: =COUNTIFS($M$7:$M$5006,">="&Q24,$M$7:$M$5006,"<"&R24) -> 122 | U24: =IF(R24<=0,T24/COUNT($M$7:$M$5006),0) -> 0 | V24: =IF(Q24>=0,T24/COUNT($M$7:$M$5006),0) -> 0.0244
B25: Fixed costs | C25: 0 | D25: =-$C$11 -> -80000 | E25: =-$C$11 -> -80000 | F25: =-$C$11 -> -80000 | G25: =-$C$11 -> -80000 | H25: =-$C$11 -> -80000 | L25: 19 | M25: -219729.1 | Q25: =R24 -> 420000 | R25: =Q25+$R$5 -> 480000 | S25: =TEXT((Q25+R25)/2000,"#,##0")&"k" -> 450k | T25: =COUNTIFS($M$7:$M$5006,">="&Q25,$M$7:$M$5006,"<"&R25) -> 83 | U25: =IF(R25<=0,T25/COUNT($M$7:$M$5006),0) -> 0 | V25: =IF(Q25>=0,T25/COUNT($M$7:$M$5006),0) -> 0.0166
B26: Free cash flow (FCF) | C26: =SUM(C22:C25) -> -800000 | D26: =SUM(D22:D25) -> 280942.38 | E26: =SUM(E22:E25) -> 280942.38 | F26: =SUM(F22:F25) -> 280942.38 | G26: =SUM(G22:G25) -> 280942.38 | H26: =SUM(H22:H25) -> 280942.38 | L26: 20 | M26: -7171.2757 | Q26: =R25 -> 480000 | R26: =Q26+$R$5 -> 540000 | S26: =TEXT((Q26+R26)/2000,"#,##0")&"k" -> 510k | T26: =COUNTIFS($M$7:$M$5006,">="&Q26,$M$7:$M$5006,"<"&R26) -> 43 | U26: =IF(R26<=0,T26/COUNT($M$7:$M$5006),0) -> 0 | V26: =IF(Q26>=0,T26/COUNT($M$7:$M$5006),0) -> 0.0086
B27: Discount factor = 1 / (1 + r)^t | C27: =1/(1+$C$12)^0 -> 1 | D27: =1/(1+$C$12)^1 -> 0.90909091 | E27: =1/(1+$C$12)^2 -> 0.82644628 | F27: =1/(1+$C$12)^3 -> 0.7513148 | G27: =1/(1+$C$12)^4 -> 0.68301346 | H27: =1/(1+$C$12)^5 -> 0.62092132 | L27: 21 | M27: 79262.441 | Q27: =R26 -> 540000 | R27: =Q27+$R$5 -> 600000 | S27: =TEXT((Q27+R27)/2000,"#,##0")&"k" -> 570k | T27: =COUNTIFS($M$7:$M$5006,">="&Q27,$M$7:$M$5006,"<"&R27) -> 17 | U27: =IF(R27<=0,T27/COUNT($M$7:$M$5006),0) -> 0 | V27: =IF(Q27>=0,T27/COUNT($M$7:$M$5006),0) -> 0.0034
B28: Present value of FCF | C28: =C26*C27 -> -800000 | D28: =D26*D27 -> 255402.16 | E28: =E26*E27 -> 232183.78 | F28: =F26*F27 -> 211076.16 | G28: =G26*G27 -> 191887.42 | H28: =H26*H27 -> 174443.11 | L28: 22 | M28: -154201.91 | Q28: =R27 -> 600000 | R28: =Q28+$R$5 -> 660000 | S28: =TEXT((Q28+R28)/2000,"#,##0")&"k" -> 630k | T28: =COUNTIFS($M$7:$M$5006,">="&Q28,$M$7:$M$5006,"<"&R28) -> 10 | U28: =IF(R28<=0,T28/COUNT($M$7:$M$5006),0) -> 0 | V28: =IF(Q28>=0,T28/COUNT($M$7:$M$5006),0) -> 0.002
L29: 23 | M29: -88290.045 | Q29: =R28 -> 660000 | R29: =Q29+$R$5 -> 720000 | S29: =TEXT((Q29+R29)/2000,"#,##0")&"k" -> 690k | T29: =COUNTIFS($M$7:$M$5006,">="&Q29,$M$7:$M$5006,"<"&R29) -> 10 | U29: =IF(R29<=0,T29/COUNT($M$7:$M$5006),0) -> 0 | V29: =IF(Q29>=0,T29/COUNT($M$7:$M$5006),0) -> 0.002
B30: Net present value (NPV) | C30: =SUM(C28:H28) -> 264992.64 | L30: 24 | M30: 233452.8 | Q30: =R29 -> 720000 | R30: =Q30+$R$5 -> 780000 | S30: =TEXT((Q30+R30)/2000,"#,##0")&"k" -> 750k | T30: =COUNTIFS($M$7:$M$5006,">="&Q30,$M$7:$M$5006,"<"&R30) -> 4 | U30: =IF(R30<=0,T30/COUNT($M$7:$M$5006),0) -> 0 | V30: =IF(Q30>=0,T30/COUNT($M$7:$M$5006),0) -> 0.0008
B31: Check: Excel NPV() + Year 0 flow | C31: =NPV($C$12,D26:H26)+C26 -> 264992.64 | D31: NPV() discounts its first flow by one period, so Year 0 is added separately. | L31: 25 | M31: -53935.746 | Q31: =R30 -> 780000 | R31: =Q31+$R$5 -> 840000 | S31: =TEXT((Q31+R31)/2000,"#,##0")&"k" -> 810k | T31: =COUNTIFS($M$7:$M$5006,">="&Q31,$M$7:$M$5006,"<"&R31) -> 3 | U31: =IF(R31<=0,T31/COUNT($M$7:$M$5006),0) -> 0 | V31: =IF(Q31>=0,T31/COUNT($M$7:$M$5006),0) -> 0.0006
L32: 26 | M32: -36110.981 | Q32: =R31 -> 840000 | R32: =Q32+$R$5 -> 900000 | S32: =TEXT((Q32+R32)/2000,"#,##0")&"k" -> 870k | T32: =COUNTIFS($M$7:$M$5006,">="&Q32,$M$7:$M$5006,"<"&R32) -> 2 | U32: =IF(R32<=0,T32/COUNT($M$7:$M$5006),0) -> 0 | V32: =IF(Q32>=0,T32/COUNT($M$7:$M$5006),0) -> 0.0004
B33: Break-even (base case, one input at a time) | C33: Value | D33: vs base case | L33: 27 | M33: -360353.65 | Q33: =R32 -> 900000 | R33: =Q33+$R$5 -> 960000 | S33: =TEXT((Q33+R33)/2000,"#,##0")&"k" -> 930k | T33: =COUNTIFS($M$7:$M$5006,">="&Q33,$M$7:$M$5006,"<"&R33) -> 0 | U33: =IF(R33<=0,T33/COUNT($M$7:$M$5006),0) -> 0 | V33: =IF(Q33>=0,T33/COUNT($M$7:$M$5006),0) -> 0
B34: Break-even price (€ / unit) | C34: =($C$7/SUM(D27:H27)+$C$11)/$C$8+$C$10 -> 49.402532 | D34: =C34/$C$9-1 -> -0.011949354 | E34: Required FCF = investment / annuity factor; solved for price or volume. | L34: 28 | M34: 161497.55 | Q34: =R33 -> 960000 | R34: =Q34+$R$5 -> 1020000 | S34: =TEXT((Q34+R34)/2000,"#,##0")&"k" -> 990k | T34: =COUNTIFS($M$7:$M$5006,">="&Q34,$M$7:$M$5006,"<"&R34) -> 0 | U34: =IF(R34<=0,T34/COUNT($M$7:$M$5006),0) -> 0 | V34: =IF(Q34>=0,T34/COUNT($M$7:$M$5006),0) -> 0
B35: Break-even volume (units / year) | C35: =($C$7/SUM(D27:H27)+$C$11)/($C$9-$C$10) -> 14551.899 | D35: =C35/$C$8-1 -> -0.029873385 | L35: 29 | M35: -49494.177 | Q35: =R34 -> 1020000 | R35: =Q35+$R$5 -> 1080000 | S35: =TEXT((Q35+R35)/2000,"#,##0")&"k" -> 1,050k | T35: =COUNTIFS($M$7:$M$5006,">="&Q35,$M$7:$M$5006,"<"&R35) -> 1 | U35: =IF(R35<=0,T35/COUNT($M$7:$M$5006),0) -> 0 | V35: =IF(Q35>=0,T35/COUNT($M$7:$M$5006),0) -> 0.0002
L36: 30 | M36: 396426.12 | Q36: =R35 -> 1080000 | R36: =Q36+$R$5 -> 1140000 | S36: =TEXT((Q36+R36)/2000,"#,##0")&"k" -> 1,110k | T36: =COUNTIFS($M$7:$M$5006,">="&Q36,$M$7:$M$5006,"<"&R36) -> 0 | U36: =IF(R36<=0,T36/COUNT($M$7:$M$5006),0) -> 0 | V36: =IF(Q36>=0,T36/COUNT($M$7:$M$5006),0) -> 0
B37: 4. Simulation results (5,000 iterations) | L37: 31 | M37: -252956.08 | Q37: =R36 -> 1140000 | R37: =Q37+$R$5 -> 1200000 | S37: =TEXT((Q37+R37)/2000,"#,##0")&"k" -> 1,170k | T37: =COUNTIFS($M$7:$M$5006,">="&Q37,$M$7:$M$5006,"<"&R37) -> 0 | U37: =IF(R37<=0,T37/COUNT($M$7:$M$5006),0) -> 0 | V37: =IF(Q37>=0,T37/COUNT($M$7:$M$5006),0) -> 0
B38: Statistic | C38: Value | D38: Excel formula | L38: 32 | M38: 228128.2 | Q38: =R37 -> 1200000 | R38: =Q38+$R$5 -> 1260000 | S38: =TEXT((Q38+R38)/2000,"#,##0")&"k" -> 1,230k | T38: =COUNTIFS($M$7:$M$5006,">="&Q38,$M$7:$M$5006,"<"&R38) -> 0 | U38: =IF(R38<=0,T38/COUNT($M$7:$M$5006),0) -> 0 | V38: =IF(Q38>=0,T38/COUNT($M$7:$M$5006),0) -> 0
B39: Mean NPV | C39: =AVERAGE($M$7:$M$5006) -> 29828.592 | D39: AVERAGE | L39: 33 | M39: -186679.16 | Q39: Coverage check | T39: =SUM(T7:T38)/COUNT($M$7:$M$5006) -> 1
B40: Standard deviation | C40: =_xlfn.STDEV.S($M$7:$M$5006) -> 205028.89 | D40: STDEV.S | L40: 34 | M40: -125713.27
B41: P5 | C41: =_xlfn.PERCENTILE.INC($M$7:$M$5006,0.05) -> -294870.05 | D41: PERCENTILE.INC | L41: 35 | M41: -266128.23
B42: P50 (median) | C42: =_xlfn.PERCENTILE.INC($M$7:$M$5006,0.5) -> 25757.624 | D42: PERCENTILE.INC | L42: 36 | M42: 295739.58
B43: P95 | C43: =_xlfn.PERCENTILE.INC($M$7:$M$5006,0.95) -> 383728.68 | D43: PERCENTILE.INC | L43: 37 | M43: -75561.951
B44: Minimum | C44: =MIN($M$7:$M$5006) -> -650452.32 | D44: MIN | L44: 38 | M44: -344283.66
B45: Maximum | C45: =MAX($M$7:$M$5006) -> 1029565.7 | D45: MAX | L45: 39 | M45: -111527.21
B46: P(NPV < 0) | C46: =COUNTIF($M$7:$M$5006,"<0")/COUNT($M$7:$M$5006) -> 0.4496 | D46: COUNTIF / COUNT | L46: 40 | M46: 176261.17
B47: SE of probability | C47: =SQRT($C$46*(1-$C$46)/COUNT($M$7:$M$5006)) -> 0.0070350528 | D47: √(p(1 − p) / n) | L47: 41 | M47: -220694.53
B48: SE of mean | C48: =$C$40/SQRT(COUNT($M$7:$M$5006)) -> 2899.5464 | D48: SD / √n | L48: 42 | M48: -169826.17
L49: 43 | M49: 45781.773
L50: 44 | M50: -216266.01
L51: 45 | M51: 145535.6
L52: 46 | M52: -263303.89
L53: 47 | M53: -317105.61
L54: 48 | M54: 154841.3
L55: 49 | M55: 89560.967
L56: 50 | M56: -30272.822
L57: 51 | M57: 93554.62
L58: 52 | M58: 60646.134
L59: 53 | M59: 92012.022
L60: 54 | M60: -167252
... L5006: 5000 | M5006: -317443.1

Sheet Justified
B1: Model 2 — Justified distributions
B2: PERT price (expert estimate), Normal demand capped by capacity, variable cost fitted on 8 data points.
B3: Blue = input · Black = formula · Yellow fill = switch / key lever · Press F9 (Mac: Cmd + =) to rerun the 5,000 iterations.
L4: Simulation (Data Table) | Q4: Histogram bins
B5: 1. Base-case inputs | L5: Iteration | M5: NPV | Q5: Bin width (€, auto) | R5: =ROUNDUP((MAX($M$7:$M$5006)-MIN($M$7:$M$5006))/30/10000,0)*10000 -> 40000
B6: Simulation switch (1 = simulation, 0 = base case) | C6: 1 | D6: ← 0 = base case, 1 = simulation | M6: =$C$40 -> 92071.244 | Q6: Lower (€) | R6: Upper (€) | S6: Midpoint | T6: Count | U6: NPV < 0 | V6: NPV ≥ 0
B7: Initial investment (€, Year 0) | C7: 800000 | L7: 1 | M7: -29448.828 | Q7: =INT(MIN($M$7:$M$5006)/$R$5)*$R$5 -> -520000 | R7: =Q7+$R$5 -> -480000 | S7: =TEXT((Q7+R7)/2000,"#,##0")&"k" -> -500k | T7: =COUNTIFS($M$7:$M$5006,">="&Q7,$M$7:$M$5006,"<"&R7) -> 6 | U7: =IF(R7<=0,T7/COUNT($M$7:$M$5006),0) -> 0.0012 | V7: =IF(Q7>=0,T7/COUNT($M$7:$M$5006),0) -> 0
B8: Volume (units / year) | C8: 15000 | L8: 2 | M8: 83450.591 | Q8: =R7 -> -480000 | R8: =Q8+$R$5 -> -440000 | S8: =TEXT((Q8+R8)/2000,"#,##0")&"k" -> -460k | T8: =COUNTIFS($M$7:$M$5006,">="&Q8,$M$7:$M$5006,"<"&R8) -> 5 | U8: =IF(R8<=0,T8/COUNT($M$7:$M$5006),0) -> 0.001 | V8: =IF(Q8>=0,T8/COUNT($M$7:$M$5006),0) -> 0
B9: Price (€ / unit) | C9: 50 | L9: 3 | M9: -80931.506 | Q9: =R8 -> -440000 | R9: =Q9+$R$5 -> -400000 | S9: =TEXT((Q9+R9)/2000,"#,##0")&"k" -> -420k | T9: =COUNTIFS($M$7:$M$5006,">="&Q9,$M$7:$M$5006,"<"&R9) -> 11 | U9: =IF(R9<=0,T9/COUNT($M$7:$M$5006),0) -> 0.0022 | V9: =IF(Q9>=0,T9/COUNT($M$7:$M$5006),0) -> 0
B10: Variable cost (€ / unit) | C10: 30 | L10: 4 | M10: -41215.939 | Q10: =R9 -> -400000 | R10: =Q10+$R$5 -> -360000 | S10: =TEXT((Q10+R10)/2000,"#,##0")&"k" -> -380k | T10: =COUNTIFS($M$7:$M$5006,">="&Q10,$M$7:$M$5006,"<"&R10) -> 19 | U10: =IF(R10<=0,T10/COUNT($M$7:$M$5006),0) -> 0.0038 | V10: =IF(Q10>=0,T10/COUNT($M$7:$M$5006),0) -> 0
B11: Fixed costs (€ / year) | C11: 80000 | L11: 5 | M11: -193428.8 | Q11: =R10 -> -360000 | R11: =Q11+$R$5 -> -320000 | S11: =TEXT((Q11+R11)/2000,"#,##0")&"k" -> -340k | T11: =COUNTIFS($M$7:$M$5006,">="&Q11,$M$7:$M$5006,"<"&R11) -> 52 | U11: =IF(R11<=0,T11/COUNT($M$7:$M$5006),0) -> 0.0104 | V11: =IF(Q11>=0,T11/COUNT($M$7:$M$5006),0) -> 0
B12: Discount rate | C12: 0.1 | L12: 6 | M12: -30268.98 | Q12: =R11 -> -320000 | R12: =Q12+$R$5 -> -280000 | S12: =TEXT((Q12+R12)/2000,"#,##0")&"k" -> -300k | T12: =COUNTIFS($M$7:$M$5006,">="&Q12,$M$7:$M$5006,"<"&R12) -> 81 | U12: =IF(R12<=0,T12/COUNT($M$7:$M$5006),0) -> 0.0162 | V12: =IF(Q12>=0,T12/COUNT($M$7:$M$5006),0) -> 0
B13: Production capacity (units / year) | C13: 17000 | L13: 7 | M13: 87143.418 | Q13: =R12 -> -280000 | R13: =Q13+$R$5 -> -240000 | S13: =TEXT((Q13+R13)/2000,"#,##0")&"k" -> -260k | T13: =COUNTIFS($M$7:$M$5006,">="&Q13,$M$7:$M$5006,"<"&R13) -> 133 | U13: =IF(R13<=0,T13/COUNT($M$7:$M$5006),0) -> 0.0266 | V13: =IF(Q13>=0,T13/COUNT($M$7:$M$5006),0) -> 0
L14: 8 | M14: 71990.936 | Q14: =R13 -> -240000 | R14: =Q14+$R$5 -> -200000 | S14: =TEXT((Q14+R14)/2000,"#,##0")&"k" -> -220k | T14: =COUNTIFS($M$7:$M$5006,">="&Q14,$M$7:$M$5006,"<"&R14) -> 228 | U14: =IF(R14<=0,T14/COUNT($M$7:$M$5006),0) -> 0.0456 | V14: =IF(Q14>=0,T14/COUNT($M$7:$M$5006),0) -> 0
B15: 2. Uncertain inputs and distributions | L15: 9 | M15: 43537.284 | Q15: =R14 -> -200000 | R15: =Q15+$R$5 -> -160000 | S15: =TEXT((Q15+R15)/2000,"#,##0")&"k" -> -180k | T15: =COUNTIFS($M$7:$M$5006,">="&Q15,$M$7:$M$5006,"<"&R15) -> 281 | U15: =IF(R15<=0,T15/COUNT($M$7:$M$5006),0) -> 0.0562 | V15: =IF(Q15>=0,T15/COUNT($M$7:$M$5006),0) -> 0
B16: Input | C16: Distribution | D16: Mean | E16: SD | F16: Min | G16: Mode | H16: Max | I16: Draw | J16: Value used | L16: 10 | M16: 1370.0795 | Q16: =R15 -> -160000 | R16: =Q16+$R$5 -> -120000 | S16: =TEXT((Q16+R16)/2000,"#,##0")&"k" -> -140k | T16: =COUNTIFS($M$7:$M$5006,">="&Q16,$M$7:$M$5006,"<"&R16) -> 353 | U16: =IF(R16<=0,T16/COUNT($M$7:$M$5006),0) -> 0.0706 | V16: =IF(Q16>=0,T16/COUNT($M$7:$M$5006),0) -> 0
B17: Price (€ / unit) | C17: PERT | D17: =(F17+4*G17+H17)/6 -> 49.333333 | F17: 44 | G17: 50 | H17: 52 | I17: =_xlfn.BETA.INV(RAND(),C22,C23,F17,H17) -> 50.366416 | J17: =IF($C$6=1,I17,$C$9) -> 50.366416 | L17: 11 | M17: -158049.59 | Q17: =R16 -> -120000 | R17: =Q17+$R$5 -> -80000 | S17: =TEXT((Q17+R17)/2000,"#,##0")&"k" -> -100k | T17: =COUNTIFS($M$7:$M$5006,">="&Q17,$M$7:$M$5006,"<"&R17) -> 457 | U17: =IF(R17<=0,T17/COUNT($M$7:$M$5006),0) -> 0.0914 | V17: =IF(Q17>=0,T17/COUNT($M$7:$M$5006),0) -> 0
B18: Demand (units / year) → units sold capped at capacity | C18: Normal | D18: 15000 | E18: 1500 | I18: =_xlfn.NORM.INV(RAND(),D18,E18) -> 15436.37 | J18: =IF($C$6=1,MIN(I18,$C$13),$C$8) -> 15436.37 | L18: 12 | M18: -216173.1 | Q18: =R17 -> -80000 | R18: =Q18+$R$5 -> -40000 | S18: =TEXT((Q18+R18)/2000,"#,##0")&"k" -> -60k | T18: =COUNTIFS($M$7:$M$5006,">="&Q18,$M$7:$M$5006,"<"&R18) -> 510 | U18: =IF(R18<=0,T18/COUNT($M$7:$M$5006),0) -> 0.102 | V18: =IF(Q18>=0,T18/COUNT($M$7:$M$5006),0) -> 0
B19: Variable cost (€ / unit) | C19: Normal (fitted) | D19: =C27 -> 30.0625 | E19: =C28 -> 1.2443443 | I19: =_xlfn.NORM.INV(RAND(),D19,E19) -> 29.938936 | J19: =IF($C$6=1,I19,$C$10) -> 29.938936 | L19: 13 | M19: -116039.57 | Q19: =R18 -> -40000 | R19: =Q19+$R$5 -> 0 | S19: =TEXT((Q19+R19)/2000,"#,##0")&"k" -> -20k | T19: =COUNTIFS($M$7:$M$5006,">="&Q19,$M$7:$M$5006,"<"&R19) -> 538 | U19: =IF(R19<=0,T19/COUNT($M$7:$M$5006),0) -> 0.1076 | V19: =IF(Q19>=0,T19/COUNT($M$7:$M$5006),0) -> 0
B20: Fixed costs (€ / year) | C20: Constant | J20: =$C$11 -> 80000 | L20: 14 | M20: -856.33995 | Q20: =R19 -> 0 | R20: =Q20+$R$5 -> 40000 | S20: =TEXT((Q20+R20)/2000,"#,##0")&"k" -> 20k | T20: =COUNTIFS($M$7:$M$5006,">="&Q20,$M$7:$M$5006,"<"&R20) -> 530 | U20: =IF(R20<=0,T20/COUNT($M$7:$M$5006),0) -> 0 | V20: =IF(Q20>=0,T20/COUNT($M$7:$M$5006),0) -> 0.106
L21: 15 | M21: 48322.251 | Q21: =R20 -> 40000 | R21: =Q21+$R$5 -> 80000 | S21: =TEXT((Q21+R21)/2000,"#,##0")&"k" -> 60k | T21: =COUNTIFS($M$7:$M$5006,">="&Q21,$M$7:$M$5006,"<"&R21) -> 426 | U21: =IF(R21<=0,T21/COUNT($M$7:$M$5006),0) -> 0 | V21: =IF(Q21>=0,T21/COUNT($M$7:$M$5006),0) -> 0.0852
B22: PERT α = 1 + 4 × (mode − min) / (max − min) | C22: =1+4*(G17-F17)/(H17-F17) -> 4 | D22: PERT mean = (min + 4 × mode + max) / 6, shown in the Mean column | L22: 16 | M22: -192299.87 | Q22: =R21 -> 80000 | R22: =Q22+$R$5 -> 120000 | S22: =TEXT((Q22+R22)/2000,"#,##0")&"k" -> 100k | T22: =COUNTIFS($M$7:$M$5006,">="&Q22,$M$7:$M$5006,"<"&R22) -> 407 | U22: =IF(R22<=0,T22/COUNT($M$7:$M$5006),0) -> 0 | V22: =IF(Q22>=0,T22/COUNT($M$7:$M$5006),0) -> 0.0814
B23: PERT β = 1 + 4 × (max − mode) / (max − min) | C23: =1+4*(H17-G17)/(H17-F17) -> 2 | L23: 17 | M23: -37052.861 | Q23: =R22 -> 120000 | R23: =Q23+$R$5 -> 160000 | S23: =TEXT((Q23+R23)/2000,"#,##0")&"k" -> 140k | T23: =COUNTIFS($M$7:$M$5006,">="&Q23,$M$7:$M$5006,"<"&R23) -> 325 | U23: =IF(R23<=0,T23/COUNT($M$7:$M$5006),0) -> 0 | V23: =IF(Q23>=0,T23/COUNT($M$7:$M$5006),0) -> 0.065
L24: 18 | M24: -15469.634 | Q24: =R23 -> 160000 | R24: =Q24+$R$5 -> 200000 | S24: =TEXT((Q24+R24)/2000,"#,##0")&"k" -> 180k | T24: =COUNTIFS($M$7:$M$5006,">="&Q24,$M$7:$M$5006,"<"&R24) -> 255 | U24: =IF(R24<=0,T24/COUNT($M$7:$M$5006),0) -> 0 | V24: =IF(Q24>=0,T24/COUNT($M$7:$M$5006),0) -> 0.051
B25: Historical variable cost (€ / unit) | C25: Period 1 | D25: Period 2 | E25: Period 3 | F25: Period 4 | G25: Period 5 | H25: Period 6 | I25: Period 7 | J25: Period 8 | L25: 19 | M25: 241737.95 | Q25: =R24 -> 200000 | R25: =Q25+$R$5 -> 240000 | S25: =TEXT((Q25+R25)/2000,"#,##0")&"k" -> 220k | T25: =COUNTIFS($M$7:$M$5006,">="&Q25,$M$7:$M$5006,"<"&R25) -> 174 | U25: =IF(R25<=0,T25/COUNT($M$7:$M$5006),0) -> 0 | V25: =IF(Q25>=0,T25/COUNT($M$7:$M$5006),0) -> 0.0348
B26: Observed value | C26: 28.5 | D26: 29 | E26: 31.2 | F26: 30.4 | G26: 29.8 | H26: 32.1 | I26: 30.6 | J26: 28.9 | L26: 20 | M26: 54746.848 | Q26: =R25 -> 240000 | R26: =Q26+$R$5 -> 280000 | S26: =TEXT((Q26+R26)/2000,"#,##0")&"k" -> 260k | T26: =COUNTIFS($M$7:$M$5006,">="&Q26,$M$7:$M$5006,"<"&R26) -> 97 | U26: =IF(R26<=0,T26/COUNT($M$7:$M$5006),0) -> 0 | V26: =IF(Q26>=0,T26/COUNT($M$7:$M$5006),0) -> 0.0194
B27: Fitted mean | C27: =AVERAGE(C26:J26) -> 30.0625 | L27: 21 | M27: -120292.22 | Q27: =R26 -> 280000 | R27: =Q27+$R$5 -> 320000 | S27: =TEXT((Q27+R27)/2000,"#,##0")&"k" -> 300k | T27: =COUNTIFS($M$7:$M$5006,">="&Q27,$M$7:$M$5006,"<"&R27) -> 63 | U27: =IF(R27<=0,T27/COUNT($M$7:$M$5006),0) -> 0 | V27: =IF(Q27>=0,T27/COUNT($M$7:$M$5006),0) -> 0.0126
B28: Fitted SD (sample, STDEV.S) | C28: =_xlfn.STDEV.S(C26:J26) -> 1.2443443 | D28: STDEV.S divides by n − 1: the SD is estimated from a sample. | L28: 22 | M28: -38936.095 | Q28: =R27 -> 320000 | R28: =Q28+$R$5 -> 360000 | S28: =TEXT((Q28+R28)/2000,"#,##0")&"k" -> 340k | T28: =COUNTIFS($M$7:$M$5006,">="&Q28,$M$7:$M$5006,"<"&R28) -> 24 | U28: =IF(R28<=0,T28/COUNT($M$7:$M$5006),0) -> 0 | V28: =IF(Q28>=0,T28/COUNT($M$7:$M$5006),0) -> 0.0048
L29: 23 | M29: 175733.55 | Q29: =R28 -> 360000 | R29: =Q29+$R$5 -> 400000 | S29: =TEXT((Q29+R29)/2000,"#,##0")&"k" -> 380k | T29: =COUNTIFS($M$7:$M$5006,">="&Q29,$M$7:$M$5006,"<"&R29) -> 17 | U29: =IF(R29<=0,T29/COUNT($M$7:$M$5006),0) -> 0 | V29: =IF(Q29>=0,T29/COUNT($M$7:$M$5006),0) -> 0.0034
B30: 3. Cash flows and NPV (one draw) | L30: 24 | M30: -216815.94 | Q30: =R29 -> 400000 | R30: =Q30+$R$5 -> 440000 | S30: =TEXT((Q30+R30)/2000,"#,##0")&"k" -> 420k | T30: =COUNTIFS($M$7:$M$5006,">="&Q30,$M$7:$M$5006,"<"&R30) -> 5 | U30: =IF(R30<=0,T30/COUNT($M$7:$M$5006),0) -> 0 | V30: =IF(Q30>=0,T30/COUNT($M$7:$M$5006),0) -> 0.001
B31: € | C31: Year 0 | D31: Year 1 | E31: Year 2 | F31: Year 3 | G31: Year 4 | H31: Year 5 | L31: 25 | M31: 165260.76 | Q31: =R30 -> 440000 | R31: =Q31+$R$5 -> 480000 | S31: =TEXT((Q31+R31)/2000,"#,##0")&"k" -> 460k | T31: =COUNTIFS($M$7:$M$5006,">="&Q31,$M$7:$M$5006,"<"&R31) -> 3 | U31: =IF(R31<=0,T31/COUNT($M$7:$M$5006),0) -> 0 | V31: =IF(Q31>=0,T31/COUNT($M$7:$M$5006),0) -> 0.0006
B32: Initial investment | C32: =-$C$7 -> -800000 | D32: 0 | E32: 0 | F32: 0 | G32: 0 | H32: 0 | L32: 26 | M32: -74542.941 | Q32: =R31 -> 480000 | R32: =Q32+$R$5 -> 520000 | S32: =TEXT((Q32+R32)/2000,"#,##0")&"k" -> 500k | T32: =COUNTIFS($M$7:$M$5006,">="&Q32,$M$7:$M$5006,"<"&R32) -> 0 | U32: =IF(R32<=0,T32/COUNT($M$7:$M$5006),0) -> 0 | V32: =IF(Q32>=0,T32/COUNT($M$7:$M$5006),0) -> 0
B33: Revenue (units × price) | C33: 0 | D33: =$J$18*$J$17 -> 777474.65 | E33: =$J$18*$J$17 -> 777474.65 | F33: =$J$18*$J$17 -> 777474.65 | G33: =$J$18*$J$17 -> 777474.65 | H33: =$J$18*$J$17 -> 777474.65 | L33: 27 | M33: 120720.02 | Q33: =R32 -> 520000 | R33: =Q33+$R$5 -> 560000 | S33: =TEXT((Q33+R33)/2000,"#,##0")&"k" -> 540k | T33: =COUNTIFS($M$7:$M$5006,">="&Q33,$M$7:$M$5006,"<"&R33) -> 0 | U33: =IF(R33<=0,T33/COUNT($M$7:$M$5006),0) -> 0 | V33: =IF(Q33>=0,T33/COUNT($M$7:$M$5006),0) -> 0
B34: Variable costs (units × variable cost) | C34: 0 | D34: =-$J$18*$J$19 -> -462148.5 | E34: =-$J$18*$J$19 -> -462148.5 | F34: =-$J$18*$J$19 -> -462148.5 | G34: =-$J$18*$J$19 -> -462148.5 | H34: =-$J$18*$J$19 -> -462148.5 | L34: 28 | M34: -79458.969 | Q34: =R33 -> 560000 | R34: =Q34+$R$5 -> 600000 | S34: =TEXT((Q34+R34)/2000,"#,##0")&"k" -> 580k | T34: =COUNTIFS($M$7:$M$5006,">="&Q34,$M$7:$M$5006,"<"&R34) -> 0 | U34: =IF(R34<=0,T34/COUNT($M$7:$M$5006),0) -> 0 | V34: =IF(Q34>=0,T34/COUNT($M$7:$M$5006),0) -> 0
B35: Fixed costs | C35: 0 | D35: =-$C$11 -> -80000 | E35: =-$C$11 -> -80000 | F35: =-$C$11 -> -80000 | G35: =-$C$11 -> -80000 | H35: =-$C$11 -> -80000 | L35: 29 | M35: 10482.484 | Q35: =R34 -> 600000 | R35: =Q35+$R$5 -> 640000 | S35: =TEXT((Q35+R35)/2000,"#,##0")&"k" -> 620k | T35: =COUNTIFS($M$7:$M$5006,">="&Q35,$M$7:$M$5006,"<"&R35) -> 0 | U35: =IF(R35<=0,T35/COUNT($M$7:$M$5006),0) -> 0 | V35: =IF(Q35>=0,T35/COUNT($M$7:$M$5006),0) -> 0
B36: Free cash flow (FCF) | C36: =SUM(C32:C35) -> -800000 | D36: =SUM(D32:D35) -> 235326.15 | E36: =SUM(E32:E35) -> 235326.15 | F36: =SUM(F32:F35) -> 235326.15 | G36: =SUM(G32:G35) -> 235326.15 | H36: =SUM(H32:H35) -> 235326.15 | L36: 30 | M36: -85353.22 | Q36: =R35 -> 640000 | R36: =Q36+$R$5 -> 680000 | S36: =TEXT((Q36+R36)/2000,"#,##0")&"k" -> 660k | T36: =COUNTIFS($M$7:$M$5006,">="&Q36,$M$7:$M$5006,"<"&R36) -> 0 | U36: =IF(R36<=0,T36/COUNT($M$7:$M$5006),0) -> 0 | V36: =IF(Q36>=0,T36/COUNT($M$7:$M$5006),0) -> 0
B37: Discount factor = 1 / (1 + r)^t | C37: =1/(1+$C$12)^0 -> 1 | D37: =1/(1+$C$12)^1 -> 0.90909091 | E37: =1/(1+$C$12)^2 -> 0.82644628 | F37: =1/(1+$C$12)^3 -> 0.7513148 | G37: =1/(1+$C$12)^4 -> 0.68301346 | H37: =1/(1+$C$12)^5 -> 0.62092132 | L37: 31 | M37: 42104.39 | Q37: =R36 -> 680000 | R37: =Q37+$R$5 -> 720000 | S37: =TEXT((Q37+R37)/2000,"#,##0")&"k" -> 700k | T37: =COUNTIFS($M$7:$M$5006,">="&Q37,$M$7:$M$5006,"<"&R37) -> 0 | U37: =IF(R37<=0,T37/COUNT($M$7:$M$5006),0) -> 0 | V37: =IF(Q37>=0,T37/COUNT($M$7:$M$5006),0) -> 0
B38: Present value of FCF | C38: =C36*C37 -> -800000 | D38: =D36*D37 -> 213932.86 | E38: =E36*E37 -> 194484.42 | F38: =F36*F37 -> 176804.02 | G38: =G36*G37 -> 160730.92 | H38: =H36*H37 -> 146119.02 | L38: 32 | M38: -92949.894 | Q38: =R37 -> 720000 | R38: =Q38+$R$5 -> 760000 | S38: =TEXT((Q38+R38)/2000,"#,##0")&"k" -> 740k | T38: =COUNTIFS($M$7:$M$5006,">="&Q38,$M$7:$M$5006,"<"&R38) -> 0 | U38: =IF(R38<=0,T38/COUNT($M$7:$M$5006),0) -> 0 | V38: =IF(Q38>=0,T38/COUNT($M$7:$M$5006),0) -> 0
L39: 33 | M39: -150090.31 | Q39: Coverage check | T39: =SUM(T7:T38)/COUNT($M$7:$M$5006) -> 1
B40: Net present value (NPV) | C40: =SUM(C38:H38) -> 92071.244 | L40: 34 | M40: -252706.03
B41: Check: Excel NPV() + Year 0 flow | C41: =NPV($C$12,D36:H36)+C36 -> 92071.244 | D41: NPV() discounts its first flow by one period, so Year 0 is added separately. | L41: 35 | M41: -160458.39
L42: 36 | M42: 156144.44
B43: Break-even (base case, one input at a time) | C43: Value | D43: vs base case | L43: 37 | M43: -43884.954
B44: Break-even price (€ / unit) | C44: =($C$7/SUM(D37:H37)+$C$11)/$C$8+$C$10 -> 49.402532 | D44: =C44/$C$9-1 -> -0.011949354 | E44: Required FCF = investment / annuity factor; solved for price or volume. | L44: 38 | M44: 52573.809
B45: Break-even volume (units / year) | C45: =($C$7/SUM(D37:H37)+$C$11)/($C$9-$C$10) -> 14551.899 | D45: =C45/$C$8-1 -> -0.029873385 | L45: 39 | M45: -221271.31
L46: 40 | M46: -2488.2598
B47: 4. Simulation results (5,000 iterations) | L47: 41 | M47: -186505.37
B48: Statistic | C48: Value | D48: Excel formula | L48: 42 | M48: 4999.1368
B49: Mean NPV | C49: =AVERAGE($M$7:$M$5006) -> -12665.029 | D49: AVERAGE | L49: 43 | M49: -31246.969
B50: Standard deviation | C50: =_xlfn.STDEV.S($M$7:$M$5006) -> 147934.49 | D50: STDEV.S | L50: 44 | M50: 136219.67
B51: P5 | C51: =_xlfn.PERCENTILE.INC($M$7:$M$5006,0.05) -> -255052.88 | D51: PERCENTILE.INC | L51: 45 | M51: 195306.12
B52: P50 (median) | C52: =_xlfn.PERCENTILE.INC($M$7:$M$5006,0.5) -> -12156.814 | D52: PERCENTILE.INC | L52: 46 | M52: 15974.031
B53: P95 | C53: =_xlfn.PERCENTILE.INC($M$7:$M$5006,0.95) -> 227328.52 | D53: PERCENTILE.INC | L53: 47 | M53: -4148.066
B54: Minimum | C54: =MIN($M$7:$M$5006) -> -515707.69 | D54: MIN | L54: 48 | M54: 139605.3
B55: Maximum | C55: =MAX($M$7:$M$5006) -> 451038.26 | D55: MAX | L55: 49 | M55: 109708.7
B56: P(NPV < 0) | C56: =COUNTIF($M$7:$M$5006,"<0")/COUNT($M$7:$M$5006) -> 0.5348 | D56: COUNTIF / COUNT | L56: 50 | M56: 93694.345
B57: SE of probability | C57: =SQRT($C$56*(1-$C$56)/COUNT($M$7:$M$5006)) -> 0.0070539203 | D57: √(p(1 − p) / n) | L57: 51 | M57: 16226.866
B58: SE of mean | C58: =$C$50/SQRT(COUNT($M$7:$M$5006)) -> 2092.1096 | D58: SD / √n | L58: 52 | M58: 66411.139
L59: 53 | M59: -32223.746
L60: 54 | M60: 178250.36
L61: 55 | M61: -94543.184
L62: 56 | M62: 68373.698
L63: 57 | M63: -177199.49
L64: 58 | M64: -150986.75
L65: 59 | M65: -39625.393
L66: 60 | M66: 316998.76
L67: 61 | M67: -80655.553
L68: 62 | M68: 142862.2
L69: 63 | M69: 76403.873
L70: 64 | M70: 63560.118
... L5006: 5000 | M5006: -122471.87

Sheet Correlated
B1: Model 3 — Correlated inputs (Gaussian copula)
B2: Same distributions as Model 2, with Price and Demand correlated through a Gaussian copula.
B3: Blue = input · Black = formula · Yellow fill = switch / key lever · Press F9 (Mac: Cmd + =) to rerun the 5,000 iterations.
L4: Simulation (Data Table) | Q4: Histogram bins
B5: 1. Base-case inputs | L5: Iteration | M5: NPV | N5: Price draw | O5: Demand draw | Q5: Bin width (€, auto) | R5: =ROUNDUP((MAX($M$7:$M$5006)-MIN($M$7:$M$5006))/30/10000,0)*10000 -> 30000
B6: Simulation switch (1 = simulation, 0 = base case) | C6: 1 | D6: ← 0 = base case, 1 = simulation | M6: =$C$45 -> 103081.38 | N6: =$I$18 -> 49.536026 | O6: =$I$19 -> 15776.818 | Q6: Lower (€) | R6: Upper (€) | S6: Midpoint | T6: Count | U6: NPV < 0 | V6: NPV ≥ 0
B7: Initial investment (€, Year 0) | C7: 800000 | L7: 1 | M7: -32434.196 | N7: 50.605277 | O7: 15307.861 | Q7: =INT(MIN($M$7:$M$5006)/$R$5)*$R$5 -> -420000 | R7: =Q7+$R$5 -> -390000 | S7: =TEXT((Q7+R7)/2000,"#,##0")&"k" -> -405k | T7: =COUNTIFS($M$7:$M$5006,">="&Q7,$M$7:$M$5006,"<"&R7) -> 3 | U7: =IF(R7<=0,T7/COUNT($M$7:$M$5006),0) -> 0.0006 | V7: =IF(Q7>=0,T7/COUNT($M$7:$M$5006),0) -> 0
B8: Volume (units / year) | C8: 15000 | L8: 2 | M8: 191036.03 | N8: 49.584879 | O8: 15706.344 | Q8: =R7 -> -390000 | R8: =Q8+$R$5 -> -360000 | S8: =TEXT((Q8+R8)/2000,"#,##0")&"k" -> -375k | T8: =COUNTIFS($M$7:$M$5006,">="&Q8,$M$7:$M$5006,"<"&R8) -> 4 | U8: =IF(R8<=0,T8/COUNT($M$7:$M$5006),0) -> 0.0008 | V8: =IF(Q8>=0,T8/COUNT($M$7:$M$5006),0) -> 0
B9: Price (€ / unit) | C9: 50 | L9: 3 | M9: -219694.64 | N9: 49.311953 | O9: 12754.894 | Q9: =R8 -> -360000 | R9: =Q9+$R$5 -> -330000 | S9: =TEXT((Q9+R9)/2000,"#,##0")&"k" -> -345k | T9: =COUNTIFS($M$7:$M$5006,">="&Q9,$M$7:$M$5006,"<"&R9) -> 11 | U9: =IF(R9<=0,T9/COUNT($M$7:$M$5006),0) -> 0.0022 | V9: =IF(Q9>=0,T9/COUNT($M$7:$M$5006),0) -> 0
B10: Variable cost (€ / unit) | C10: 30 | L10: 4 | M10: -71596.213 | N10: 47.307315 | O10: 18109.407 | Q10: =R9 -> -330000 | R10: =Q10+$R$5 -> -300000 | S10: =TEXT((Q10+R10)/2000,"#,##0")&"k" -> -315k | T10: =COUNTIFS($M$7:$M$5006,">="&Q10,$M$7:$M$5006,"<"&R10) -> 19 | U10: =IF(R10<=0,T10/COUNT($M$7:$M$5006),0) -> 0.0038 | V10: =IF(Q10>=0,T10/COUNT($M$7:$M$5006),0) -> 0
B11: Fixed costs (€ / year) | C11: 80000 | L11: 5 | M11: 1867.7032 | N11: 49.594372 | O11: 16658.791 | Q11: =R10 -> -300000 | R11: =Q11+$R$5 -> -270000 | S11: =TEXT((Q11+R11)/2000,"#,##0")&"k" -> -285k | T11: =COUNTIFS($M$7:$M$5006,">="&Q11,$M$7:$M$5006,"<"&R11) -> 35 | U11: =IF(R11<=0,T11/COUNT($M$7:$M$5006),0) -> 0.007 | V11: =IF(Q11>=0,T11/COUNT($M$7:$M$5006),0) -> 0
B12: Discount rate | C12: 0.1 | L12: 6 | M12: -62542.866 | N12: 50.072582 | O12: 15125.078 | Q12: =R11 -> -270000 | R12: =Q12+$R$5 -> -240000 | S12: =TEXT((Q12+R12)/2000,"#,##0")&"k" -> -255k | T12: =COUNTIFS($M$7:$M$5006,">="&Q12,$M$7:$M$5006,"<"&R12) -> 64 | U12: =IF(R12<=0,T12/COUNT($M$7:$M$5006),0) -> 0.0128 | V12: =IF(Q12>=0,T12/COUNT($M$7:$M$5006),0) -> 0
B13: Production capacity (units / year) | C13: 17000 | L13: 7 | M13: 12265.434 | N13: 47.919754 | O13: 14729.774 | Q13: =R12 -> -240000 | R13: =Q13+$R$5 -> -210000 | S13: =TEXT((Q13+R13)/2000,"#,##0")&"k" -> -225k | T13: =COUNTIFS($M$7:$M$5006,">="&Q13,$M$7:$M$5006,"<"&R13) -> 115 | U13: =IF(R13<=0,T13/COUNT($M$7:$M$5006),0) -> 0.023 | V13: =IF(Q13>=0,T13/COUNT($M$7:$M$5006),0) -> 0
B14: Price–Demand correlation (ρ) | C14: -0.5 | L14: 8 | M14: 7069.5027 | N14: 47.829625 | O14: 14495.1 | Q14: =R13 -> -210000 | R14: =Q14+$R$5 -> -180000 | S14: =TEXT((Q14+R14)/2000,"#,##0")&"k" -> -195k | T14: =COUNTIFS($M$7:$M$5006,">="&Q14,$M$7:$M$5006,"<"&R14) -> 158 | U14: =IF(R14<=0,T14/COUNT($M$7:$M$5006),0) -> 0.0316 | V14: =IF(Q14>=0,T14/COUNT($M$7:$M$5006),0) -> 0
L15: 9 | M15: 409716.18 | N15: 50.679467 | O15: 17172.451 | Q15: =R14 -> -180000 | R15: =Q15+$R$5 -> -150000 | S15: =TEXT((Q15+R15)/2000,"#,##0")&"k" -> -165k | T15: =COUNTIFS($M$7:$M$5006,">="&Q15,$M$7:$M$5006,"<"&R15) -> 254 | U15: =IF(R15<=0,T15/COUNT($M$7:$M$5006),0) -> 0.0508 | V15: =IF(Q15>=0,T15/COUNT($M$7:$M$5006),0) -> 0
B16: 2. Uncertain inputs and distributions | L16: 10 | M16: -62179.082 | N16: 50.075741 | O16: 13079.138 | Q16: =R15 -> -150000 | R16: =Q16+$R$5 -> -120000 | S16: =TEXT((Q16+R16)/2000,"#,##0")&"k" -> -135k | T16: =COUNTIFS($M$7:$M$5006,">="&Q16,$M$7:$M$5006,"<"&R16) -> 321 | U16: =IF(R16<=0,T16/COUNT($M$7:$M$5006),0) -> 0.0642 | V16: =IF(Q16>=0,T16/COUNT($M$7:$M$5006),0) -> 0
B17: Input | C17: Distribution | D17: Mean | E17: SD | F17: Min | G17: Mode | H17: Max | I17: Draw | J17: Value used | L17: 11 | M17: -72216.966 | N17: 51.082899 | O17: 12855.613 | Q17: =R16 -> -120000 | R17: =Q17+$R$5 -> -90000 | S17: =TEXT((Q17+R17)/2000,"#,##0")&"k" -> -105k | T17: =COUNTIFS($M$7:$M$5006,">="&Q17,$M$7:$M$5006,"<"&R17) -> 416 | U17: =IF(R17<=0,T17/COUNT($M$7:$M$5006),0) -> 0.0832 | V17: =IF(Q17>=0,T17/COUNT($M$7:$M$5006),0) -> 0
B18: Price (€ / unit) | C18: PERT | D18: =(F18+4*G18+H18)/6 -> 49.333333 | F18: 44 | G18: 50 | H18: 52 | I18: =_xlfn.BETA.INV(G32,C23,C24,F18,H18) -> 49.536026 | J18: =IF($C$6=1,I18,$C$9) -> 49.536026 | L18: 12 | M18: -25471.189 | N18: 49.782963 | O18: 14809.418 | Q18: =R17 -> -90000 | R18: =Q18+$R$5 -> -60000 | S18: =TEXT((Q18+R18)/2000,"#,##0")&"k" -> -75k | T18: =COUNTIFS($M$7:$M$5006,">="&Q18,$M$7:$M$5006,"<"&R18) -> 436 | U18: =IF(R18<=0,T18/COUNT($M$7:$M$5006),0) -> 0.0872 | V18: =IF(Q18>=0,T18/COUNT($M$7:$M$5006),0) -> 0
B19: Demand (units / year) → units sold capped at capacity | C19: Normal | D19: 15000 | E19: 1500 | I19: =_xlfn.NORM.INV(H32,D19,E19) -> 15776.818 | J19: =IF($C$6=1,MIN(I19,$C$13),$C$8) -> 15776.818 | L19: 13 | M19: -182457.84 | N19: 50.731448 | O19: 13707.836 | Q19: =R18 -> -60000 | R19: =Q19+$R$5 -> -30000 | S19: =TEXT((Q19+R19)/2000,"#,##0")&"k" -> -45k | T19: =COUNTIFS($M$7:$M$5006,">="&Q19,$M$7:$M$5006,"<"&R19) -> 508 | U19: =IF(R19<=0,T19/COUNT($M$7:$M$5006),0) -> 0.1016 | V19: =IF(Q19>=0,T19/COUNT($M$7:$M$5006),0) -> 0
B20: Variable cost (€ / unit) | C20: Normal (fitted) | D20: =C28 -> 30.0625 | E20: =C29 -> 1.2443443 | I20: =_xlfn.NORM.INV(RAND(),D20,E20) -> 29.365255 | J20: =IF($C$6=1,I20,$C$10) -> 29.365255 | L20: 14 | M20: 17552.901 | N20: 50.934466 | O20: 14060.97 | Q20: =R19 -> -30000 | R20: =Q20+$R$5 -> 0 | S20: =TEXT((Q20+R20)/2000,"#,##0")&"k" -> -15k | T20: =COUNTIFS($M$7:$M$5006,">="&Q20,$M$7:$M$5006,"<"&R20) -> 457 | U20: =IF(R20<=0,T20/COUNT($M$7:$M$5006),0) -> 0.0914 | V20: =IF(Q20>=0,T20/COUNT($M$7:$M$5006),0) -> 0
B21: Fixed costs (€ / year) | C21: Constant | J21: =$C$11 -> 80000 | L21: 15 | M21: -74997.804 | N21: 48.719704 | O21: 15359.913 | Q21: =R20 -> 0 | R21: =Q21+$R$5 -> 30000 | S21: =TEXT((Q21+R21)/2000,"#,##0")&"k" -> 15k | T21: =COUNTIFS($M$7:$M$5006,">="&Q21,$M$7:$M$5006,"<"&R21) -> 469 | U21: =IF(R21<=0,T21/COUNT($M$7:$M$5006),0) -> 0 | V21: =IF(Q21>=0,T21/COUNT($M$7:$M$5006),0) -> 0.0938
L22: 16 | M22: -48737.113 | N22: 50.124658 | O22: 13718.614 | Q22: =R21 -> 30000 | R22: =Q22+$R$5 -> 60000 | S22: =TEXT((Q22+R22)/2000,"#,##0")&"k" -> 45k | T22: =COUNTIFS($M$7:$M$5006,">="&Q22,$M$7:$M$5006,"<"&R22) -> 424 | U22: =IF(R22<=0,T22/COUNT($M$7:$M$5006),0) -> 0 | V22: =IF(Q22>=0,T22/COUNT($M$7:$M$5006),0) -> 0.0848
B23: PERT α = 1 + 4 × (mode − min) / (max − min) | C23: =1+4*(G18-F18)/(H18-F18) -> 4 | D23: PERT mean = (min + 4 × mode + max) / 6, shown in the Mean column | L23: 17 | M23: 153987.2 | N23: 50.819577 | O23: 15943.762 | Q23: =R22 -> 60000 | R23: =Q23+$R$5 -> 90000 | S23: =TEXT((Q23+R23)/2000,"#,##0")&"k" -> 75k | T23: =COUNTIFS($M$7:$M$5006,">="&Q23,$M$7:$M$5006,"<"&R23) -> 348 | U23: =IF(R23<=0,T23/COUNT($M$7:$M$5006),0) -> 0 | V23: =IF(Q23>=0,T23/COUNT($M$7:$M$5006),0) -> 0.0696
B24: PERT β = 1 + 4 × (max − mode) / (max − min) | C24: =1+4*(H18-G18)/(H18-F18) -> 2 | L24: 18 | M24: -39952.691 | N24: 50.860612 | O24: 15067.332 | Q24: =R23 -> 90000 | R24: =Q24+$R$5 -> 120000 | S24: =TEXT((Q24+R24)/2000,"#,##0")&"k" -> 105k | T24: =COUNTIFS($M$7:$M$5006,">="&Q24,$M$7:$M$5006,"<"&R24) -> 289 | U24: =IF(R24<=0,T24/COUNT($M$7:$M$5006),0) -> 0 | V24: =IF(Q24>=0,T24/COUNT($M$7:$M$5006),0) -> 0.0578
L25: 19 | M25: -24055.996 | N25: 47.247084 | O25: 15781.909 | Q25: =R24 -> 120000 | R25: =Q25+$R$5 -> 150000 | S25: =TEXT((Q25+R25)/2000,"#,##0")&"k" -> 135k | T25: =COUNTIFS($M$7:$M$5006,">="&Q25,$M$7:$M$5006,"<"&R25) -> 237 | U25: =IF(R25<=0,T25/COUNT($M$7:$M$5006),0) -> 0 | V25: =IF(Q25>=0,T25/COUNT($M$7:$M$5006),0) -> 0.0474
B26: Historical variable cost (€ / unit) | C26: Period 1 | D26: Period 2 | E26: Period 3 | F26: Period 4 | G26: Period 5 | H26: Period 6 | I26: Period 7 | J26: Period 8 | L26: 20 | M26: 189832.84 | N26: 50.584428 | O26: 14278.727 | Q26: =R25 -> 150000 | R26: =Q26+$R$5 -> 180000 | S26: =TEXT((Q26+R26)/2000,"#,##0")&"k" -> 165k | T26: =COUNTIFS($M$7:$M$5006,">="&Q26,$M$7:$M$5006,"<"&R26) -> 165 | U26: =IF(R26<=0,T26/COUNT($M$7:$M$5006),0) -> 0 | V26: =IF(Q26>=0,T26/COUNT($M$7:$M$5006),0) -> 0.033
B27: Observed value | C27: 28.5 | D27: 29 | E27: 31.2 | F27: 30.4 | G27: 29.8 | H27: 32.1 | I27: 30.6 | J27: 28.9 | L27: 21 | M27: -102295.35 | N27: 48.852832 | O27: 15756.096 | Q27: =R26 -> 180000 | R27: =Q27+$R$5 -> 210000 | S27: =TEXT((Q27+R27)/2000,"#,##0")&"k" -> 195k | T27: =COUNTIFS($M$7:$M$5006,">="&Q27,$M$7:$M$5006,"<"&R27) -> 115 | U27: =IF(R27<=0,T27/COUNT($M$7:$M$5006),0) -> 0 | V27: =IF(Q27>=0,T27/COUNT($M$7:$M$5006),0) -> 0.023
B28: Fitted mean | C28: =AVERAGE(C27:J27) -> 30.0625 | L28: 22 | M28: -262928.81 | N28: 47.315089 | O28: 15091.131 | Q28: =R27 -> 210000 | R28: =Q28+$R$5 -> 240000 | S28: =TEXT((Q28+R28)/2000,"#,##0")&"k" -> 225k | T28: =COUNTIFS($M$7:$M$5006,">="&Q28,$M$7:$M$5006,"<"&R28) -> 68 | U28: =IF(R28<=0,T28/COUNT($M$7:$M$5006),0) -> 0 | V28: =IF(Q28>=0,T28/COUNT($M$7:$M$5006),0) -> 0.0136
B29: Fitted SD (sample, STDEV.S) | C29: =_xlfn.STDEV.S(C27:J27) -> 1.2443443 | D29: STDEV.S divides by n − 1: the SD is estimated from a sample. | L29: 23 | M29: -56102.041 | N29: 49.864946 | O29: 13960.724 | Q29: =R28 -> 240000 | R29: =Q29+$R$5 -> 270000 | S29: =TEXT((Q29+R29)/2000,"#,##0")&"k" -> 255k | T29: =COUNTIFS($M$7:$M$5006,">="&Q29,$M$7:$M$5006,"<"&R29) -> 43 | U29: =IF(R29<=0,T29/COUNT($M$7:$M$5006),0) -> 0 | V29: =IF(Q29>=0,T29/COUNT($M$7:$M$5006),0) -> 0.0086
L30: 24 | M30: 108189.68 | N30: 49.580925 | O30: 15139.182 | Q30: =R29 -> 270000 | R30: =Q30+$R$5 -> 300000 | S30: =TEXT((Q30+R30)/2000,"#,##0")&"k" -> 285k | T30: =COUNTIFS($M$7:$M$5006,">="&Q30,$M$7:$M$5006,"<"&R30) -> 18 | U30: =IF(R30<=0,T30/COUNT($M$7:$M$5006),0) -> 0 | V30: =IF(Q30>=0,T30/COUNT($M$7:$M$5006),0) -> 0.0036
B31: Gaussian copula (one draw) | C31: Z₁ | D31: Z₂ | E31: X₁ = Z₁ | F31: X₂ = ρZ₁ + √(1−ρ²)Z₂ | G31: U₁ = Φ(X₁) | H31: U₂ = Φ(X₂) | L31: 25 | M31: -176302.1 | N31: 48.107549 | O31: 15343.161 | Q31: =R30 -> 300000 | R31: =Q31+$R$5 -> 330000 | S31: =TEXT((Q31+R31)/2000,"#,##0")&"k" -> 315k | T31: =COUNTIFS($M$7:$M$5006,">="&Q31,$M$7:$M$5006,"<"&R31) -> 14 | U31: =IF(R31<=0,T31/COUNT($M$7:$M$5006),0) -> 0 | V31: =IF(Q31>=0,T31/COUNT($M$7:$M$5006),0) -> 0.0028
B32: Independent normals → correlated → probabilities | C32: =_xlfn.NORM.S.INV(RAND()) -> 0.029653338 | D32: =_xlfn.NORM.S.INV(RAND()) -> 0.61511524 | E32: =C32 -> 0.029653338 | F32: =$C$14*C32+SQRT(1-$C$14^2)*D32 -> 0.51787876 | G32: =_xlfn.NORM.S.DIST(E32,TRUE) -> 0.51182824 | H32: =_xlfn.NORM.S.DIST(F32,TRUE) -> 0.69772857 | L32: 26 | M32: -136163.19 | N32: 48.71348 | O32: 14747.495 | Q32: =R31 -> 330000 | R32: =Q32+$R$5 -> 360000 | S32: =TEXT((Q32+R32)/2000,"#,##0")&"k" -> 345k | T32: =COUNTIFS($M$7:$M$5006,">="&Q32,$M$7:$M$5006,"<"&R32) -> 5 | U32: =IF(R32<=0,T32/COUNT($M$7:$M$5006),0) -> 0 | V32: =IF(Q32>=0,T32/COUNT($M$7:$M$5006),0) -> 0.001
B33: Price = PERT⁻¹(U₁) · Demand = Normal⁻¹(U₂) · Variable cost stays independent | L33: 27 | M33: -181188.23 | N33: 49.343377 | O33: 12747.582 | Q33: =R32 -> 360000 | R33: =Q33+$R$5 -> 390000 | S33: =TEXT((Q33+R33)/2000,"#,##0")&"k" -> 375k | T33: =COUNTIFS($M$7:$M$5006,">="&Q33,$M$7:$M$5006,"<"&R33) -> 1 | U33: =IF(R33<=0,T33/COUNT($M$7:$M$5006),0) -> 0 | V33: =IF(Q33>=0,T33/COUNT($M$7:$M$5006),0) -> 0.0002
L34: 28 | M34: -37026.188 | N34: 49.349032 | O34: 14471.698 | Q34: =R33 -> 390000 | R34: =Q34+$R$5 -> 420000 | S34: =TEXT((Q34+R34)/2000,"#,##0")&"k" -> 405k | T34: =COUNTIFS($M$7:$M$5006,">="&Q34,$M$7:$M$5006,"<"&R34) -> 1 | U34: =IF(R34<=0,T34/COUNT($M$7:$M$5006),0) -> 0 | V34: =IF(Q34>=0,T34/COUNT($M$7:$M$5006),0) -> 0.0002
B35: 3. Cash flows and NPV (one draw) | L35: 29 | M35: -176368.77 | N35: 47.264091 | O35: 15938.993 | Q35: =R34 -> 420000 | R35: =Q35+$R$5 -> 450000 | S35: =TEXT((Q35+R35)/2000,"#,##0")&"k" -> 435k | T35: =COUNTIFS($M$7:$M$5006,">="&Q35,$M$7:$M$5006,"<"&R35) -> 2 | U35: =IF(R35<=0,T35/COUNT($M$7:$M$5006),0) -> 0 | V35: =IF(Q35>=0,T35/COUNT($M$7:$M$5006),0) -> 0.0004
B36: € | C36: Year 0 | D36: Year 1 | E36: Year 2 | F36: Year 3 | G36: Year 4 | H36: Year 5 | L36: 30 | M36: -142412.23 | N36: 46.946218 | O36: 15085.636 | Q36: =R35 -> 450000 | R36: =Q36+$R$5 -> 480000 | S36: =TEXT((Q36+R36)/2000,"#,##0")&"k" -> 465k | T36: =COUNTIFS($M$7:$M$5006,">="&Q36,$M$7:$M$5006,"<"&R36) -> 0 | U36: =IF(R36<=0,T36/COUNT($M$7:$M$5006),0) -> 0 | V36: =IF(Q36>=0,T36/COUNT($M$7:$M$5006),0) -> 0
B37: Initial investment | C37: =-$C$7 -> -800000 | D37: 0 | E37: 0 | F37: 0 | G37: 0 | H37: 0 | L37: 31 | M37: 51403.698 | N37: 47.739323 | O37: 15484.32 | Q37: =R36 -> 480000 | R37: =Q37+$R$5 -> 510000 | S37: =TEXT((Q37+R37)/2000,"#,##0")&"k" -> 495k | T37: =COUNTIFS($M$7:$M$5006,">="&Q37,$M$7:$M$5006,"<"&R37) -> 0 | U37: =IF(R37<=0,T37/COUNT($M$7:$M$5006),0) -> 0 | V37: =IF(Q37>=0,T37/COUNT($M$7:$M$5006),0) -> 0
B38: Revenue (units × price) | C38: 0 | D38: =$J$19*$J$18 -> 781520.88 | E38: =$J$19*$J$18 -> 781520.88 | F38: =$J$19*$J$18 -> 781520.88 | G38: =$J$19*$J$18 -> 781520.88 | H38: =$J$19*$J$18 -> 781520.88 | L38: 32 | M38: 90934.594 | N38: 50.036593 | O38: 15125.593 | Q38: =R37 -> 510000 | R38: =Q38+$R$5 -> 540000 | S38: =TEXT((Q38+R38)/2000,"#,##0")&"k" -> 525k | T38: =COUNTIFS($M$7:$M$5006,">="&Q38,$M$7:$M$5006,"<"&R38) -> 0 | U38: =IF(R38<=0,T38/COUNT($M$7:$M$5006),0) -> 0 | V38: =IF(Q38>=0,T38/COUNT($M$7:$M$5006),0) -> 0
B39: Variable costs (units × variable cost) | C39: 0 | D39: =-$J$19*$J$20 -> -463290.28 | E39: =-$J$19*$J$20 -> -463290.28 | F39: =-$J$19*$J$20 -> -463290.28 | G39: =-$J$19*$J$20 -> -463290.28 | H39: =-$J$19*$J$20 -> -463290.28 | L39: 33 | M39: -2965.7962 | N39: 47.786599 | O39: 15596.113 | Q39: Coverage check | T39: =SUM(T7:T38)/COUNT($M$7:$M$5006) -> 1
B40: Fixed costs | C40: 0 | D40: =-$C$11 -> -80000 | E40: =-$C$11 -> -80000 | F40: =-$C$11 -> -80000 | G40: =-$C$11 -> -80000 | H40: =-$C$11 -> -80000 | L40: 34 | M40: -260139.03 | N40: 47.829237 | O40: 13911.674
B41: Free cash flow (FCF) | C41: =SUM(C37:C40) -> -800000 | D41: =SUM(D37:D40) -> 238230.59 | E41: =SUM(E37:E40) -> 238230.59 | F41: =SUM(F37:F40) -> 238230.59 | G41: =SUM(G37:G40) -> 238230.59 | H41: =SUM(H37:H40) -> 238230.59 | L41: 35 | M41: -35887.035 | N41: 49.918969 | O41: 15241.591
B42: Discount factor = 1 / (1 + r)^t | C42: =1/(1+$C$12)^0 -> 1 | D42: =1/(1+$C$12)^1 -> 0.90909091 | E42: =1/(1+$C$12)^2 -> 0.82644628 | F42: =1/(1+$C$12)^3 -> 0.7513148 | G42: =1/(1+$C$12)^4 -> 0.68301346 | H42: =1/(1+$C$12)^5 -> 0.62092132 | L42: 36 | M42: 12598.429 | N42: 50.202509 | O42: 15326.94
B43: Present value of FCF | C43: =C41*C42 -> -800000 | D43: =D41*D42 -> 216573.27 | E43: =E41*E42 -> 196884.79 | F43: =F41*F42 -> 178986.17 | G43: =G41*G42 -> 162714.7 | H43: =H41*H42 -> 147922.46 | L43: 37 | M43: -77357.647 | N43: 50.498978 | O43: 13195.431
L44: 38 | M44: 120502.76 | N44: 50.897483 | O44: 15738.977
B45: Net present value (NPV) | C45: =SUM(C43:H43) -> 103081.38 | L45: 39 | M45: -165742.08 | N45: 49.653177 | O45: 13614.082
B46: Check: Excel NPV() + Year 0 flow | C46: =NPV($C$12,D41:H41)+C41 -> 103081.38 | D46: NPV() discounts its first flow by one period, so Year 0 is added separately. | L46: 40 | M46: 151676.5 | N46: 49.862557 | O46: 16325.811
L47: 41 | M47: 46363.227 | N47: 50.081426 | O47: 15564.289
B48: Break-even (base case, one input at a time) | C48: Value | D48: vs base case | L48: 42 | M48: -79183.7 | N48: 49.751983 | O48: 13985.799
B49: Break-even price (€ / unit) | C49: =($C$7/SUM(D42:H42)+$C$11)/$C$8+$C$10 -> 49.402532 | D49: =C49/$C$9-1 -> -0.011949354 | E49: Required FCF = investment / annuity factor; solved for price or volume. | L49: 43 | M49: -82630.051 | N49: 44.792896 | O49: 17378.696
B50: Break-even volume (units / year) | C50: =($C$7/SUM(D42:H42)+$C$11)/($C$9-$C$10) -> 14551.899 | D50: =C50/$C$8-1 -> -0.029873385 | L50: 44 | M50: 17250.352 | N50: 48.731286 | O50: 15416.41
L51: 45 | M51: -58314.382 | N51: 49.989305 | O51: 14434.088
B52: 4. Simulation results (5,000 iterations) | L52: 46 | M52: -10994.042 | N52: 49.679185 | O52: 15041.426
B53: Statistic | C53: Value | D53: Excel formula | L53: 47 | M53: -37558.805 | N53: 49.400647 | O53: 14409.943
B54: Mean NPV | C54: =AVERAGE($M$7:$M$5006) -> -16730.853 | D54: AVERAGE | L54: 48 | M54: -15216.566 | N54: 48.209953 | O54: 16038.185
B55: Standard deviation | C55: =_xlfn.STDEV.S($M$7:$M$5006) -> 119980.21 | D55: STDEV.S | L55: 49 | M55: -153594.15 | N55: 47.523074 | O55: 15424.563
B56: P5 | C56: =_xlfn.PERCENTILE.INC($M$7:$M$5006,0.05) -> -210726.62 | D56: PERCENTILE.INC | L56: 50 | M56: 28091.681 | N56: 48.405119 | O56: 15734.522
B57: P50 (median) | C57: =_xlfn.PERCENTILE.INC($M$7:$M$5006,0.5) -> -19685.516 | D57: PERCENTILE.INC | L57: 51 | M57: 114154.12 | N57: 49.38363 | O57: 14962.918
B58: P95 | C58: =_xlfn.PERCENTILE.INC($M$7:$M$5006,0.95) -> 182281.06 | D58: PERCENTILE.INC | L58: 52 | M58: -62460.557 | N58: 48.402435 | O58: 13008.242
B59: Minimum | C59: =MIN($M$7:$M$5006) -> -415956.41 | D59: MIN | L59: 53 | M59: 37473.852 | N59: 47.976912 | O59: 15350.919
B60: Maximum | C60: =MAX($M$7:$M$5006) -> 447480.5 | D60: MAX | L60: 54 | M60: -136647.48 | N60: 47.351978 | O60: 15404.929
B61: P(NPV < 0) | C61: =COUNTIF($M$7:$M$5006,"<0")/COUNT($M$7:$M$5006) -> 0.5602 | D61: COUNTIF / COUNT | L61: 55 | M61: -130416.17 | N61: 49.727696 | O61: 13500.066
B62: SE of probability | C62: =SQRT($C$61*(1-$C$61)/COUNT($M$7:$M$5006)) -> 0.0070196291 | D62: √(p(1 − p) / n) | L62: 56 | M62: -68400.698 | N62: 49.458035 | O62: 13474.321
B63: SE of mean | C63: =$C$55/SQRT(COUNT($M$7:$M$5006)) -> 1696.7764 | D63: SD / √n | L63: 57 | M63: 15405.026 | N63: 50.290421 | O63: 13752.002
B64: Correlation check: CORREL(price, demand draws) | C64: =CORREL($N$7:$N$5006,$O$7:$O$5006) -> -0.49169328 | D64: CORREL (target: ρ) | L64: 58 | M64: 88216.352 | N64: 50.871164 | O64: 14443.531
L65: 59 | M65: -20241.165 | N65: 51.013746 | O65: 13664.063
L66: 60 | M66: -26560.377 | N66: 46.994751 | O66: 16178.801
L67: 61 | M67: -171529.72 | N67: 50.422962 | O67: 11845.274
L68: 62 | M68: -45707.563 | N68: 47.393572 | O68: 15356.116
L69: 63 | M69: -232746.55 | N69: 46.350178 | O69: 14384.305
L70: 64 | M70: -32214.565 | N70: 50.538601 | O70: 13790.152
L71: 65 | M71: 36853.199 | N71: 50.340262 | O71: 14874.994
L72: 66 | M72: -222636.25 | N72: 49.336252 | O72: 13039.435
L73: 67 | M73: 7795.5909 | N73: 50.245525 | O73: 13881.957
L74: 68 | M74: 119605.02 | N74: 47.542698 | O74: 17149.055
L75: 69 | M75: -170537.41 | N75: 47.854244 | O75: 15502.641
L76: 70 | M76: -59799.062 | N76: 50.264957 | O76: 14164.685
... L85: 79 | M85: -188621.21 | N85: 47.410789 | O85: 12829.259
B86: 6. Effect of ρ — stored results (three Excel runs of 5,000 iterations, values pasted) | L86: 80 | M86: 173006.58 | N86: 49.775664 | O86: 15723.285
B87: Statistic | C87: ρ = −0.5 | D87: ρ = 0 | E87: ρ = +0.5 | L87: 81 | M87: -93306.478 | N87: 49.934318 | O87: 14845.026
B88: Mean NPV | C88: -16704 | D88: -14735 | E88: -10357 | L88: 82 | M88: 120170.18 | N88: 47.971247 | O88: 17471.075
B89: Standard deviation | C89: 117181 | D89: 147353 | E89: 172201 | L89: 83 | M89: -47427.547 | N89: 50.623024 | O89: 13174.376
B90: P5 | C90: -211927 | D90: -257480 | E90: -294505 | L90: 84 | M90: -40779.323 | N90: 49.019004 | O90: 13493.73
B91: P50 (median) | C91: -18039 | D91: -16481 | E91: -8394 | L91: 85 | M91: 15222.333 | N91: 49.820014 | O91: 14341.408
B92: P95 | C92: 176025 | D92: 233871 | E92: 266853 | L92: 86 | M92: -4745.1663 | N92: 49.966253 | O92: 15037.24
B93: P(NPV < 0) | C93: 0.5616 | D93: 0.5406 | E93: 0.5152 | L93: 87 | M93: -165164.38 | N93: 48.498159 | O93: 15212.235
B94: Correlation check | C94: -0.5106 | D94: 0.0068 | E94: 0.4828 | L94: 88 | M94: -128153.59 | N94: 50.044411 | O94: 12330.07
B95: Reading: a negative Price–Demand correlation narrows the spread (natural hedge) but lowers the mean, since E[P × V] = E[P]E[V] + Cov(P, V). | L95: 89 | M95: -96251.087 | N95: 48.852431 | O95: 14166.289
L96: 90 | M96: 69671.856 | N96: 48.151485 | O96: 16212.724
L97: 91 | M97: 95258.069 | N97: 49.70791 | O97: 15964.65
L98: 92 | M98: 94209.908 | N98: 49.549076 | O98: 15241.455
L99: 93 | M99: 36467.732 | N99: 48.985554 | O99: 15449.205
L100: 94 | M100: -99490.902 | N100: 51.112644 | O100: 12701.538
L101: 95 | M101: 32974.293 | N101: 50.931999 | O101: 14246.907
L102: 96 | M102: 12257.82 | N102: 47.320887 | O102: 16196.356
L103: 97 | M103: -71492.436 | N103: 47.587701 | O103: 16525.636
L104: 98 | M104: 21818.19 | N104: 49.990874 | O104: 14853.995
L105: 99 | M105: 92943.546 | N105: 49.126598 | O105: 17837.049
L106: 100 | M106: -340044.79 | N106: 50.73279 | O106: 12091.746
L107: 101 | M107: 181523.94 | N107: 50.688852 | O107: 16136.274
... L5006: 5000 | M5006: -5329.9672 | N5006: 50.429585 | O5006: 14621.508

Sheet Validation
B1: Validation — Excel vs Python
B2: The same models were rebuilt in Python (NumPy / SciPy) and run with 1,000,000 iterations. A gap is consistent with sampling noise when |z| < 2.
B3: z = (Excel − Python) / √(SE_Excel² + SE_Python²). Excel values are live: they change with every recalculation (F9).
B5: Excel (5,000 iterations, live) vs Python (1,000,000 iterations, seed 42)
B6: Model | C6: Statistic | D6: Excel | E6: SE Excel | F6: Python | G6: SE Python | H6: z-score | I6: Status
B7: Independent | C7: Mean NPV | D7: =Independent!$C$39 -> 29828.592 | E7: =Independent!$C$48 -> 2899.5464 | F7: 34037.33 | G7: 201.77 | H7: =(D7-F7)/SQRT(E7^2+G7^2) -> -1.4480144 | I7: =IF(ABS(H7)<2,"Consistent","Check") -> Consistent
C8: P(NPV < 0) | D8: =Independent!$C$46 -> 0.4496 | E8: =Independent!$C$47 -> 0.0070350528 | F8: 0.447853 | G8: 0.000497 | H8: =(D8-F8)/SQRT(E8^2+G8^2) -> 0.24771054 | I8: =IF(ABS(H8)<2,"Consistent","Check") -> Consistent
B9: Justified | C9: Mean NPV | D9: =Justified!$C$49 -> -12665.029 | E9: =Justified!$C$58 -> 2092.1096 | F9: -11940.12 | G9: 147.58 | H9: =(D9-F9)/SQRT(E9^2+G9^2) -> -0.34563793 | I9: =IF(ABS(H9)<2,"Consistent","Check") -> Consistent
C10: P(NPV < 0) | D10: =Justified!$C$56 -> 0.5348 | E10: =Justified!$C$57 -> 0.0070539203 | F10: 0.531927 | G10: 0.000499 | H10: =(D10-F10)/SQRT(E10^2+G10^2) -> 0.40627596 | I10: =IF(ABS(H10)<2,"Consistent","Check") -> Consistent
B11: Correlated | C11: Mean NPV | D11: =Correlated!$C$54 -> -16730.853 | E11: =Correlated!$C$63 -> 1696.7764 | F11: -15687.58 | G11: 119.28 | H11: =(D11-F11)/SQRT(E11^2+G11^2) -> -0.61334253 | I11: =IF(ABS(H11)<2,"Consistent","Check") -> Consistent
C12: P(NPV < 0) | D12: =Correlated!$C$61 -> 0.5602 | E12: =Correlated!$C$62 -> 0.0070196291 | F12: 0.557533 | G12: 0.000497 | H12: =(D12-F12)/SQRT(E12^2+G12^2) -> 0.37898589 | I12: =IF(ABS(H12)<2,"Consistent","Check") -> Consistent
B14: Python implementation, tests and an ASML DCF case study: github.com/YacineHaddouche/monte-carlo-valuation
